{"the_vent": {"comment": ["starbucks", "gaming", "BoJackHorseman", "GetMotivated", "Showerthoughts", "Overwatch", "AMA", "MvC3", "NoStupidQuestions", "TrueOffMyChest", "depression", "makemychoice", "Screenwriting", "educationalgifs", "funny", "Advice", "Ijustwatched", "FrenchHouse", "howtonotgiveafuck", "LongDistance", "socialskills", "Anxiety", "adventuretime", "TwoBestFriendsPlay", "EOOD", "sandiego", "leaves", "DoesAnybodyElse", "DaftPunk", "foxes", "Resolutions", "Stoicism", "CasualConversation", "politics", "needadvice", "offmychest", "Vent", "animemusic", "learnart", "AskWomen", "lostgeneration", "AskReddit", "Anger", "pics", "webcomics", "freelance", "aww", "resumes", "fullmoviesonyoutube", "selflove", "quotes", "ADHD", "mylittlepony", "explainlikeimfive", "comics", "socialanxiety", "memes", "anime", "csun", "DecidingToBeBetter", "GifRecipes", "GetEmployed", "videos", "reactiongifs", "badroommates", "confession", "news", "college", "pictureswithpatrick", "movies", "food", "AskMen", "StreetFighter", "pan_media", "AdviceAnimals", "WTF", "jobs", "careerguidance", "animation", "findapath", "mega64", "gifs", "trees"], "submission": ["starbucks", "gaming", "Showerthoughts", "NoStupidQuestions", "depression", "makemychoice", "Ijustwatched", "Advice", "Anxiety", "FrenchHouse", "LongDistance", "howtonotgiveafuck", "socialskills", "leaves", "Resolutions", "needadvice", "Vent", "offmychest", "animemusic", "whatsbotheringyou", "AskWomen", "AskReddit", "Anger", "freelance", "resumes", "ADHD", "explainlikeimfive", "socialanxiety", "badroommates", "confession", "college", "StreetFighter", "AskMen", "introvert", "AdviceAnimals", "jobs", "careerguidance", "findapath", "UnsentLetters", "u_the_vent", "trees"]}, "Dutchie333": {"comment": ["relationship_advice", "AskReddit", "dating_advice", "gifs"], "submission": ["offmychest", "dating_advice", "depression", "AskReddit", "Advice", "relationship_advice", "AskEurope"]}, "peachyduckss": {"comment": ["teenagers", "delusionalartists", "Advice", "starterpacks", "raisedbynarcissists"], "submission": ["heartbreak", "teenagers", "delusionalartists", "r4r", "relationship_advice", "Pizza", "Instagramreality", "Advice", "starterpacks", "raisedbynarcissists", "BadMUAs"]}, "gunner7517": {"comment": ["clashroyaleclans", "DataHoarder", "Overwatch", "Amd", "MechanicalKeyboards", "Steam", "2meirl4meirl", "gameofthrones", "mocktheguyatgastation", "LinusTechTips", "fatbirds", "TwoRedditorsOneCup", "thisismylifenow", "fo4", "nvidia", "silhouWHAT", "intrusivethoughts", "AnimalsBeingDerps", "KidsAreFuckingStupid", "barkour", "FreeKarma4You", "TheRedPill", "ooerintensifies", "holdmyjuicebox", "SummerReddit", "u_kn0thing", "Robocraft", "IdiotsOnBikes", "AndroidMasterRace", "BannedFromThe_Donald", "polandball", "CheeseandRiceReddit", "LinuxOnThinkpad", "matt", "Doom", "IncrediblesMemes", "HighQualityReloads", "CatsAreAssholes", "ImGoingToHellForThis", "GTAV", "steelseries", "pcreich", "unexpectedgordanramsy", "nononono", "Y2K", "TyrionWinsTheThrone", "SouthDakota", "Whatthefuckgetitoffme", "MemeEconomy", "yesyesyesyesno", "PBSOD", "ITcrowd", "CatTaps", "sysadmin", "instantkarma", "patientgamers", "windowsxp", "bigboye", "WTF", "delusionalartists", "Justfuckmyshitup", "dadsdone", "homelab", "ClashOfClansRecruit", "GameDeals", "holdmyfries", "battlestations", "StarWars", "holdmyredbull", "tifu", "IdiotsFightingThings", "TeamDonkeyMan", "ATAAE", "RoastMe", "blackmagicfuckery", "tooktoomuch", "hitmanimals", "IllegalLifeProTips", "Harambe", "System76", "marijuanaenthusiasts", "VanHelsingTV", "politics", "timesplitters", "The_Donald", "asubforeverything", "fightporn", "shittykickstarters", "Iwidkhtr", "lostredditors", "photoshopbattles", "SiouxFalls", "onewordeach", "IceFishing", "ihadastroke", "player3hasjoined", "HighwayFightSquad", "Whatcouldgowrong", "rickandmorty", "thinkpad", "diablo3", "trashy", "howtonotgiveafuck", "ofcoursethatsathing", "GamePhysics", "dontdeadopeninside", "Fallout", "linuxmemes", "TheITcrowd", "TIHI", "linuxhardware", "nomorals", "gaminggifs", "tarantinogifs", "instantbarbarians", "videos", "Android", "me_irl", "Diablo", "notinteresting", "dataisbeautiful", "youdrinkbathwater", "texts", "AccidentalRenaissance", "reverseanimalrescue", "im14andthisisdeep", "NoMansSkyTheGame", "noisygifs", "porn", "BoomBeach", "cyberpunkgame", "tippytaps", "meirl", "killingfloor", "FellowKids", "terriblefacebookmemes", "fivenightsatfreddys", "WordAvalanches", "Stickfight", "Coronavirus", "okbuddyretard", "howtokeepanidiotbusy", "darksouls3", "CentOS", "ARK", "fuckepic", "cantsleep", "freefolk", "Advice", "HumansBeingBros", "hmmm", "FuckYouKaren", "reallifedoodles", "Creampie_Porn", "buildapcsales", "Emuwarflashbacks", "slammywhammies", "Minecraft", "wtfstockphotos", "Pigifs", "assholedesign", "titanfall", "Bossfight", "religion", "itsaunixsystem", "computers", "SuddenlyGay", "evilbuildings", "catpranks", "PublicFreakout", "Colorado", "HybridAnimals", "pcgaming", "GTBAE", "awwtf", "microsoftsoftwareswap", "macsetups", "antipetamovement", "therewasanattempt", "donthelpjustfilm", "pussypassdenied", "WeHaveSeenTheButthole", "cars", "tobleronetits", "unixporn", "WatchPeopleDieInside", "GrandTheftAutoV", "techsupportgore", "ShoebillStorks", "raining", "holdmyturban", "CrossCountry", "Laughlin", "IAmA", "waterniggas", "TooAfraidToAsk", "Project_Ascension", "wholesomememes", "roomdetective", "ItTheMovie", "holdmyfeedingtube", "linuxmasterrace", "JusticeServed", "youdontsurf", "nexus6", "nottheonion", "CozyPlaces", "whowouldwin", "PeopleFuckingDying", "MinimalWallpaper", "RedditPotluck", "fo76", "wow", "trashpandas", "funny", "technicallythetruth", "linux_gaming", "SubsYouFellFor", "Thorgasm", "IsTodayFridayThe13th", "overclocking", "UNBGBBIIVCHIDCTIICBG", "whatisthisthing", "OldSchoolCool", "Avatar", "AndroidGaming", "wowthanksimcured", "PRTwitter", "phonebatterylevelbot", "ActLikeYouBelong", "PartyParrot", "teenagers", "hdmemes", "nonononoyes", "NeckbeardNests", "pcmasterrace", "dontputyourdickinthat", "WinStupidPrizes", "thanosdidnothingwrong", "iamverysmart", "asoiaf", "SubredditSimMeta", "microsoftsucks", "hardwareswap", "beetlejuicing", "eternium", "ClashRoyale", "Zoomies", "rwcs", "MechanicAdvice", "doot", "shittytechnicals", "SneakyBackgroundFeet", "track", "LinuxOnThinkpads", "AbruptChaos", "Teleshits", "techsupport", "peoplefuckingliving", "ForeverAlone", "totallynotrobots", "nintendo", "dogswithjobs", "linux4noobs", "Dreams", "MidgetsFightingThings", "linux", "riskofrain", "AnimalsFailing", "shittyoverusedmemes", "StoppedWorking", "technews", "HighQualityGifs", "BlackPeopleTwitter", "AnimalTextGifs", "nothingeverhappens", "thehatedone", "ProperAnimalNames", "sodadungeon", "neckbeardRPG", "debian", "AskOuija", "AyyMD", "blunderyears", "2healthbars", "starterpacks", "gaming", "southpark", "forbiddensnacks", "dankmemes", "bannedfromclubpenguin", "raspberry_pi", "bobiverse", "masterhacker", "videocards", "WorldofTanks", "theydidtheincestmath", "apple", "maybemaybemaybe", "theydidthefuckyou", "SkyrimTogether", "NormalDayInArabia", "armwrestling", "itookapicture", "Bioshock", "inspirobot", "modpiracy", "confession", "news", "FinalFantasy", "reddittriforce", "ThatLookedExpensive", "chromeos", "greentext", "ihaveihaveihavereddit", "depression", "shittybattlestations", "JustinY", "China", "skyrim", "archlinux", "AccurateBattleSim", "nextfuckinglevel", "halo", "jesuschristreddit", "suggestapc", "IdiotsInCars", "CatastrophicFailure", "titleporn", "literallyfightporn", "area51", "fakehistoryporn", "admincraft", "YouSeeComrade", "China_Flu", "EggsInStrangePlaces", "relationship_advice", "personalfinance", "uptimeporn", "Matthew", "CatsISUOTTATFO", "UnexpectedMorshuKing", "running", "AnimalsBeingJerks", "Xiaomi", "TheLastAirbender", "AskReddit", "ClashOfClans", "Fedora", "technology", "comics", "boombeachrecruit", "GrandTheftAutoV_PC", "theocho", "subredditoftheday", "Owls", "unpopularopinion", "Gunsmoke", "GTAVpc", "nonononoyesno"], "submission": ["clashroyaleclans", "techsupport", "evilbuildings", "Overwatch", "Amd", "MechanicalKeyboards", "linux4noobs", "DiWHY", "Dreams", "linux", "riskofrain", "The_Donald", "GameRoomPC", "technews", "TalesFromRetail", "MiniaturePinscher", "cars", "sodadungeon", "WatchPeopleDieInside", "AskOuija", "AyyMD", "SiouxFalls", "nvidia", "birthofasub", "CrossCountry", "gaming", "thinkpad", "diablo3", "ShadowBan", "youtube", "Project_Ascension", "Robocraft", "theydidthefuckyou", "AndroidMasterRace", "linuxmasterrace", "JusticeServed", "nexus6", "matt", "nottheonion", "Doom", "whowouldwin", "reddittriforce", "Disturbed", "Android", "notinteresting", "AskDocs", "fo76", "math", "funny", "FORTnITE", "linux_gaming", "shittybattlestations", "overclocking", "learnprogramming", "killingfloor", "whatisthisthing", "sysadmin", "AccurateBattleSim", "fivenightsatfreddys", "Monitors", "patientgamers", "WordAvalanches", "area51", "pcmasterrace", "admincraft", "darksouls3", "iamverysmart", "ARK", "Advice", "personalfinance", "homelab", "uptimeporn", "ClashOfClansRecruit", "running", "buildapcsales", "AskReddit", "ClashOfClans", "Minecraft", "ClashRoyale", "AskNetsec", "samsung", "MechanicAdvice", "unpopularopinion", "assholedesign", "religion", "Westereros"]}, "heyfreesamples": {"comment": ["BikiniBottomTwitter", "vegan", "LoveIslandTV", "thebachelor", "atheism", "funny", "Advice", "relationship_advice", "therewasanattempt", "SandersForPresident", "BoneAppleTea", "AskReddit", "veganfitness", "lastimages", "Zoomies", "antiMLM", "beyondthebump", "breakingmom", "SkincareAddiction", "Assistance", "LuLaNo", "Youniqueamua", "ShittyVeganFoodPorn", "BeautyGuruChatter", "vegancirclejerk", "LosAngeles", "SAHP", "universalstudios", "Instagramreality", "BadMUAs"], "submission": ["BikiniBottomTwitter", "vegan", "thebachelor", "DunderMifflin", "bugbites", "funny", "Advice", "relationship_advice", "TheRightCantMeme", "therewasanattempt", "SandersForPresident", "awfuleyebrows", "veganfitness", "lastimages", "Botchedsurgeries", "Zoomies", "antiMLM", "insanepeoplefacebook", "beyondthebump", "GoogleMaps", "breakingmom", "SkincareAddiction", "pugs", "ShittyVeganFoodPorn", "vegancirclejerk", "LoveIsBlindOnNetflix", "BadMUAs", "LosAngeles", "PiratePets", "universalstudios", "Instagramreality", "BoneAppleTea"]}, "EmptyIcon": {"comment": ["Advice"], "submission": ["Advice", "advise", "iaido"]}, "ConsciousAttention": {"comment": ["DreamInterpretation", "ptsd", "OCPoetry", "depression", "getting_over_it", "Advice"], "submission": ["DreamInterpretation", "ptsd", "OCPoetry", "UnsentLetters", "depression", "PrayerRequests", "Advice"]}, "IxVisionLoathes": {"comment": ["Advice", "sex", "NoFap", "dating_advice"], "submission": ["Fitness", "sex", "AskDocs", "dating_advice", "Vaping101", "Advice", "NoFap", "u_IxVisionLoathes"]}, "icarusthefifth": {"comment": ["Jokes", "BikiniBottomTwitter", "firstworldanarchists", "interestingasfuck", "IAmA", "nononono", "sports", "garlicoin", "PornhubComments", "WhitePeopleTwitter", "MemeEconomy", "wallstreetbets", "AskReddit", "OldSchoolCool", "pics", "todayilearned", "EarthPorn", "quityourbullshit", "MURICA", "BetterEveryLoop", "memes", "wicked_edge", "JamesBond", "mildlyinteresting", "Wellthatsucks", "food", "unpopularopinion", "AskOuija", "Bitcoin", "movies", "AskMen", "TheSimpsons", "MovieDetails", "Sat"], "submission": ["Jokes", "BikiniBottomTwitter", "iamverysmart", "Showerthoughts", "NoStupidQuestions", "hitmanimals", "TooAfraidToAsk", "funny", "Advice", "CrazyIdeas", "OutOfTheLoop", "PornhubComments", "perfectloops", "theydidthemath", "AskWomen", "APStudents", "OldSchoolCool", "AskReddit", "holdmybeer", "holdmyfries", "BillBurr", "todayilearned", "EarthPorn", "chanceme", "mildlyinfuriating", "MURICA", "wicked_edge", "JamesBond", "mildlyinteresting", "tifu", "ShittyLifeProTips", "news", "onionhate", "unpopularopinion", "CircleofTrust", "MovieDetails", "highschool"]}, "2veryicey": {"comment": ["DataHoarder", "nocontext", "london", "interestingasfuck", "Showerthoughts", "canada", "Random_Acts_Of_Pizza", "smalldickproblems", "TalesFromYourServer", "RoomPorn", "dankchristianmemes", "NatureIsFuckingLit", "AskHistory", "DrunkOrAKid", "TalesFromTheCustomer", "sneksnekTalk", "uselessredcircle", "pics", "EarthPorn", "insanepeoplefacebook", "fifthworldproblems", "happy", "Documentaries", "MURICA", "Lightbulb", "lostredditors", "mildyinteresting", "WatchPeopleDieInside", "Badfaketexts", "AskOuija", "movies", "techsupportgore", "space", "LucidDreaming", "Music", "gifs", "starterpacks", "keto", "Ohio", "TalesFromThePharmacy", "Jokes", "gaming", "darkjokes", "vaxxhappened", "nosleep", "engrish", "IAmA", "trashy", "britishproblems", "DesignPorn", "softwaregore", "wokekids", "StoriesAboutKevin", "tsgonewildstories", "ofcoursethatsathing", "MaliciousCompliance", "Dueling", "masterhacker", "nostalgia", "apple", "todayilearned", "Tensingstories", "HailCorporate", "AskVet", "woof_irl", "talesfromtechsupport", "linuxmasterrace", "flags_irl", "UpliftingNews", "nottheonion", "videos", "history", "science", "AntiJokes", "food", "news", "ModSupport", "confession", "Unexpected", "ideasfortheadmins", "dataisbeautiful", "trippinthroughtime", "Pareidolia", "CatsAreAssholes", "WhatsInThisBox", "TwoSentenceHorror", "harrypotter", "europe", "Scotland", "UnethicalLifeProTips", "outside", "PerilousPlatypus", "futureworldleaders", "TwoXChromosomes", "MadeMeSmile", "ArchitecturePorn", "funny", "AnimalsBeingBros", "AprilKnights", "nickofnight", "ChildrenFallingOver", "WritingPrompts", "AccidentalRacism", "CircleOfTrustMeta", "FoodPorn", "onejob", "writing", "OldSchoolCool", "Drugs", "aww", "CatTaps", "listentothis", "quityourbullshit", "explainlikeimfive", "cosmoandwanda", "selfies", "mildlyinteresting", "jesuschristreddit", "teenagers", "BritishSuccess", "gadgets", "AntiAntiJokes", "montypython", "CircleofTrust", "legere", "Futurology", "ProgrammerHumor", "MurderedByWords", "aprilfools", "GoldReplies", "petrichorparticle", "MeanJokes", "OopsDidntMeanTo", "AskUK", "CheeseAndRice", "TalesFromTheFrontDesk", "worldnews", "ChoosingBeggars", "MurderMystery2", "books", "TrueOffMyChest", "SubredditSimMeta", "minecraftsuggestions", "Advice", "SweatyPalms", "theydidthemonstermath", "SiriFail", "Trumpgret", "CasualUK", "WhitePeopleTwitter", "creepy", "DIY", "test", "ScottishPeopleTwitter", "HistoryMemes", "AskReddit", "CrappyDesign", "Minecraft", "LittleJohnny", "google", "mildyinfuriating", "iamverybadass", "needamod", "ANormalDayInRussia", "thermaltake", "sneksnek", "SUBREDDITNAME", "RedditSilverRobot", "4chan", "ukpolitics", "phoenixprojects", "thatHappened", "adoptareddit", "tifu", "bugs", "assholedesign", "AnimalsBeingConfused", "buildapc", "Catculations", "suspiciousquotes", "StardewValley", "IDontWorkHereLady", "FREE", "2b2t"], "submission": ["Jokes", "gaming", "darkjokes", "nocontext", "techsupport", "CatsBeingAssholes", "Showerthoughts", "outside", "softwaregore", "SubredditSimMeta", "minecraftsuggestions", "AntiJakes", "funny", "Advice", "Wales", "LifeProTips", "MaliciousCompliance", "UnexpectedOuija", "WritingPrompts", "AskHistory", "HistoryWhatIf", "creepy", "FoodPorn", "meirl", "onejob", "writing", "AskReddit", "Minecraft", "u_2veryicey", "askscience", "mildyinfuriating", "AskVet", "changemyview", "aww", "fifthworldproblems", "linuxmasterrace", "thermaltake", "quityourbullshit", "explainlikeimfive", "mildlyinfuriating", "sneksnek", "Lightbulb", "mildlyinteresting", "phoenixprojects", "tifu", "adoptareddit", "thatHappened", "jesuschristreddit", "food", "photoshopbattles", "AskOuija", "itcaughtoninaflash", "assholedesign", "montypython", "subreddit", "me_irl", "MyPeopleNeedMe", "CircleofTrust", "buildapc", "legere", "LucidDreaming", "ideasfortheadmins", "redditsilver", "ProgrammerHumor", "MurderedByWords", "StardewValley", "keto", "WhatsInThisBox", "TwoSentenceHorror", "2b2t"]}, "johnnyreynny": {"comment": [], "submission": ["ComedyCemetery", "Layer", "comedyheaven", "Advice", "pics"]}, "ffrfffffvy4": {"comment": ["Advice"], "submission": ["Advice"]}, "throwaway7758832": {"comment": ["Advice"], "submission": ["Advice"]}, "Top_Guns_Iceman": {"comment": ["leagueoflegends", "GreenBayPackers", "politics", "personalfinance", "nfl", "AskReddit", "Advice", "oddlysatisfying", "aww", "HumansBeingBros", "pics"], "submission": ["GreenBayPackers", "AskReddit", "Advice", "aww", "personalfinance"]}, "johngakey": {"comment": ["blackmagicfuckery", "interestingasfuck", "Showerthoughts", "ArtCrit", "translator", "nintendo", "mildlyterrifying", "DidThisLastNight", "NintendoSwitch", "therewasanattempt", "SnapLenses", "pics", "tipofmytongue", "CODZombies", "tipofmypenis", "television", "Art", "lostredditors", "awfuleverything", "movies", "TimAndEric", "net_neutrality", "PS4", "cursedcomments", "KidsAreFuckingStupid", "Music", "ClimateOffensive", "gifs", "medizzy", "u_dontneedurl", "youseeingthisshit", "Jokes", "gaming", "firetvstick", "JonTron", "nosleep", "bald", "AwesomeOffBrands", "questions", "IAmA", "forbiddensnacks", "softwaregore", "bonehurtingjuice", "TooAfraidToAsk", "n64", "dontdeadopeninside", "meme", "maybemaybemaybe", "todayilearned", "woooosh", "TIHI", "nukedmemes", "ComedyNecrophilia", "TittyDrop", "psx", "nottheonion", "UpliftingNews", "sbubby", "science", "videos", "RetroPie", "surrealmemes", "PeopleFuckingDying", "food", "news", "DCcomics", "gtaonline", "justa", "medical", "retrogaming", "misleadingthumbnails", "4PanelCringe", "SmashBrosUltimate", "ClimateActionPlan", "SeriousConversation", "greentext", "philosophy", "AskDocs", "AMA", "im14andthisisdeep", "snes", "Anthpo", "funny", "instant_regret", "AccidentalRacism", "rant", "CasualConversation", "datamoshing", "nes", "OldSchoolCool", "whatisthisthing", "tipofmyjoystick", "aww", "woahdude", "listentothis", "quityourbullshit", "explainlikeimfive", "doodles", "TheMonkeysPaw", "mildlyinteresting", "BeAmazed", "DidntKnowIWantedThat", "Wellthatsucks", "youngpeopleyoutube", "okbuddyretard", "Futurology", "MurderedByWords", "MarioMaker", "gifsthatkeepongiving", "blursedimages", "Blackops4", "RocketLeagueExchange", "BikiniBottomTwitter", "delusionalartists", "hittableFaces", "worldnews", "books", "SweetHomeAlabama", "crappyoffbrands", "HumansBeingBros", "cellphones", "hardwaregore", "AAAAAAAAAAAAAAAAA", "creepy", "RocketLeague", "Question", "MAME", "AskReddit", "bingbongtheorem", "toastme", "changemyview", "PowderToy", "mildlyinfuriating", "boottoobig", "imsorryjon", "tifu", "Games", "ComedyCemetery", "IDAP", "holdmycosmo", "Damnthatsinteresting"], "submission": ["gaming", "RocketLeagueExchange", "SmashBrosUltimate", "firetvstick", "SeriousConversation", "hittableFaces", "bald", "greentext", "questions", "AskDocs", "AMA", "snes", "ArtCrit", "TooAfraidToAsk", "Advice", "translator", "Computer_Tech_Help", "cellphones", "Python", "NintendoSwitch", "arcade", "Layer", "rant", "RocketLeague", "CasualConversation", "datamoshing", "nes", "Balding", "MAME", "whatisthisthing", "AskReddit", "tipofmyjoystick", "aww", "tipofmytongue", "changemyview", "PowderToy", "CODZombies", "tipofmypenis", "explainlikeimfive", "doodles", "emulation", "TheMonkeysPaw", "project64", "RetroPie", "videos", "Wellthatsucks", "ComedyCemetery", "IDAP", "DCcomics", "TimAndEric", "junjiito", "PS4", "net_neutrality", "gtaonline", "ClimateOffensive", "medical"]}, "kellylee93": {"comment": ["apexlegends", "adorableporn", "iPhoneX", "apolloapp", "dankmemes", "TwoXChromosomes", "funny", "Advice", "instant_regret", "adventuretime", "gonewild", "BattlefrontTWO", "WorldofTanks", "iphone", "Depersonalization", "WorldofTanksConsole", "PCBuilds", "AskReddit", "runescape", "airsoft", "cumsluts", "PewdiepieSubmissions", "PetiteGoneWild", "xbox", "Art", "mildlyinteresting", "nottheonion", "WorldOfTanksBlitz", "tifu", "news", "unpopularopinion", "LegalTeens", "watchpeopledie", "Android", "gifs", "StarWarsBattlefront"], "submission": ["unpopularopinion", "WorldOfWarshipsBlitz", "BattlefrontTWO", "runescape", "bathroomgraffitiporn", "iPhoneX", "WorldofTanksConsole", "PCBuilds", "Advice", "AskReddit", "funny", "airsoft", "pics", "WorldOfTanksBlitz", "BattlefieldLFG"]}, "throw_throw_1623": {"comment": ["Advice"], "submission": ["Advice"]}, "justmyprivate": {"comment": ["Advice", "tipofmypenis", "AskReddit", "HomeworkHelp"], "submission": ["Advice", "sex", "tipofmypenis", "HomeworkHelp"]}, "hooddolphen": {"comment": ["findasubreddit", "Money", "offmychest", "TalesFromTheCustomer", "LeagueOfMemes", "Cloud9", "pics", "sonamains", "KarmaRoulette", "SimsMobile", "legaladvice", "BlackPeopleTwitter", "AskAnAmerican", "awfuleverything", "jobs", "AskHistorians", "AnimalsBeingDerps", "ihadastroke", "KidsAreFuckingStupid", "amumumains", "amiugly", "cheatatmathhomework", "FullShrimp", "STD", "FedEx", "TooAfraidToAsk", "leagueoflegends", "MaliciousCompliance", "confidentlyincorrect", "ManifestNBC", "maybemaybemaybe", "laptops", "FullScorpion", "AskVet", "thereifixedit", "WallpaperRequests", "videos", "LGBTeens", "Dominos", "KitchenConfidential", "kindness", "HumanTippyTaps", "UnethicalLifeProTips", "noshitouija", "funny", "watchpeoplesurvive", "doordash", "AskLEO", "MaleFashionMarket", "13ReasonsWhy", "CasualConversation", "SantasLittleHelpers", "onejob", "DunkinDonuts", "Agoraphobia", "daddit", "summonerschool", "oddlyspecific", "WeEatBees", "SuddenlyIncest", "slavelabour", "CongratsLikeImFive", "ActLikeYouBelong", "BeAmazed", "teenagers", "IdiotsNearlyDying", "CopOrNot", "casualiama", "IdiotsInCars", "WinStupidPrizes", "AskHR", "IDmydog", "popping", "TeamfightTactics", "nunumains", "deadbydaylight", "LeagueConnect", "DecisionsWereMade", "NoStupidQuestions", "juul", "Advice", "Godtierpickuplines", "AmItheAsshole", "LifeProTips", "relationship_advice", "insaneparents", "MaddenMobileForums", "SampleSize", "supportlol", "AskReddit", "warwickmains", "yassuoNA", "neekomains", "supergirlTV", "nevertellmetheodds", "ApplyingToCollege", "agedlikemilk", "Toontown", "The100", "assholedesign", "imveryedgy", "ivernmains", "Fitness", "dayton", "blackpeoplegifs", "HomeworkHelp", "BreakUps", "mildlypenis", "ParentsAreFuckingDumb"], "submission": ["stopsmoking", "STD", "LeagueConnect", "NoStupidQuestions", "snapchat", "juul", "Advice", "relationship_advice", "DoesAnybodyElse", "AskLEO", "personalfinance", "leagueoflegends", "DirtySnapchat", "MaddenMobileForums", "domesticviolence", "SantasLittleHelpers", "offmychest", "DunkinDonuts", "warwickmains", "AskVet", "summonerschool", "legaladvice", "slavelabour", "ShouldIbuythisgame", "The100", "KitchenConfidential", "dayton", "HomeworkHelp", "AskHR", "kitchenticketfails"]}, "throwaway8273729": {"comment": ["Advice"], "submission": ["Advice"]}, "Snowflake0o0": {"comment": ["northernireland", "polymerclay", "RoastMe", "iamverysmart", "worldnews", "expeditionsviking", "hapas", "OrthodoxChristianity", "britishproblems", "Sikh", "CatholicMemes", "conspiracy", "motorcyclememes", "dankchristianmemes", "Buddhism", "aznidentity", "socialism", "u_badwhetter", "politics", "justneckbeardthings", "eurovision", "wallstreetbets", "China", "korea", "Christians", "The_Donald", "ireland", "democrats", "otaku", "GoogleMaps", "Catholicism", "ChapoTrapHouse", "minipainting", "poland", "VietNam", "MMORPG", "Israel", "ShouldIbuythisgame", "Judaism", "popheads", "neckbeardRPG", "unpopularopinion", "LabourUK", "greatawakening", "Christianity", "Chinesetourists", "religion", "asiantwoX", "Music", "fakehistoryporn", "mixedrace", "painting"], "submission": ["DivinityOriginalSin", "northernireland", "EasternSunRising", "polymerclay", "hapas", "OrthodoxChristianity", "Bible", "CatholicMemes", "worldcup", "Advice", "motorcyclememes", "japan", "dankchristianmemes", "Buddhism", "EnoughCommieSpam", "soccer", "aznidentity", "whiteknighting", "needadvice", "TrueCatholicPolitics", "asian", "football", "AskReddit", "China", "korea", "weeaboo", "WhiteRights", "ireland", "Christians", "rpg", "Palestine", "otaku", "GoogleMaps", "Catholicism", "minipainting", "poland", "VietNam", "MMORPG", "Art", "asianamerican", "raisedbynarcissists", "Judaism", "unpopularopinion", "motorcycles", "FULLCOMMUNISM", "Christianity", "painting", "religion", "ios", "asiantwoX", "racism", "cancer", "arabs", "starterpacks", "EasternCatholic", "mixedrace", "Catholic"]}, "DoomUnit_X2": {"comment": ["stopsmoking", "skeptic", "Showerthoughts", "pcgaming", "Harmontown", "offmychest", "Health", "Otters", "clutchband", "NonZeroDay", "pics", "antinatalism", "podcasts", "tressless", "pregnant", "hotsaucerecipes", "ToolBand", "legaladvice", "socialanxiety", "bois", "schizophrenia", "blunderyears", "UnpopularOpinions", "stopdrinking", "themarsvolta", "Jokes", "AteTheOnion", "bald", "SuicideWatch", "Disgaea", "LearnJapanese", "Vent", "futurefunk", "BokuNoHeroAcademia", "todayilearned", "drums", "OkCupid", "ShouldIbuythisgame", "UpliftingNews", "SocialSecurity", "science", "DesignMyRoom", "blacksabbath", "PeopleFuckingDying", "WebGames", "hotsauce", "AskMen", "dating_advice", "PixelArt", "nightvale", "Portland", "piano", "AMA", "Animesuggest", "deepseacreatures", "depression", "Hardcore", "DoesAnybodyElse", "tattoos", "Crunchyroll", "CasualConversation", "PrequelMemes", "adventuregames", "shittyfoodporn", "Ghosts", "explainlikeimfive", "LearnUselessTalents", "migraine", "mildlyinteresting", "oddlysatisfying", "StandUpComedy", "GetMotivated", "sex", "mentalhealth", "Advice", "furry", "LifeProTips", "ChurchofFroppy", "GameDeals", "misophonia", "AskReddit", "stonerrock", "technology", "drone", "ShowerOrange", "mildlyinfuriating", "Sneakers", "anime", "OCD", "progresspics", "NosleepAudio", "wikipedia", "unpopularopinion", "Fitness", "oyajigag", "doommetal", "EDM"], "submission": ["Jokes", "relationships", "stopsmoking", "GetMotivated", "bald", "Showerthoughts", "sex", "piano", "AMA", "circlejerk", "Animesuggest", "depression", "Advice", "SubChats", "furry", "DoesAnybodyElse", "LifeProTips", "Hardcore", "SuicideWatch", "ChurchofFroppy", "Crunchyroll", "LearnJapanese", "Buddhism", "EmoScreamo", "Guitar", "CasualConversation", "EyeFloaters", "offmychest", "Dreams", "Vent", "AskWomen", "misophonia", "AskReddit", "fantanoforever", "Decor", "stonerrock", "todayilearned", "podcasts", "tressless", "drums", "Ghosts", "legaladvice", "OkCupid", "Metal", "socialanxiety", "Sneakers", "migraine", "matheducation", "mildlyinteresting", "anime", "OCD", "SocialSecurity", "MicrosoftWord", "oddlysatisfying", "DesignMyRoom", "wikipedia", "ShowerThroughts", "hotsauce", "unpopularopinion", "AskMen", "redesign", "jobs", "schizophrenia", "dating_advice", "Music", "amiugly", "UnpopularOpinions", "stopdrinking", "malepatternbaldness", "nightvale", "doommetal", "EDM"]}, "Loggerfrog": {"comment": ["rccars", "slotcars", "darkmemes", "spaceengineers", "ElegooMars", "wastelandwarfare", "AskReddit", "OffGridCabins", "Advice", "suspiciouslyspecific", "woodworking"], "submission": ["blursedimages", "destiny2", "rccars", "britishproblems", "darkmemes", "AskReddit", "Advice"]}, "plasticanimal": {"comment": ["IAmA", "NoStupidQuestions", "atheism", "TheDollop", "funny", "Advice", "GuerrillaGardening", "ShittyEarthPorn", "Bonsai", "marijuanaenthusiasts", "alcohol", "offmychest", "AskReddit", "humor", "pics", "aww", "todayilearned", "shittyfoodporn", "FoodToronto", "drunkencookery", "mildlyinfuriating", "whatsthisplant", "videos", "homestead", "AdviceAnimals", "WTF", "Music", "howardstern", "SquareFootGardening"], "submission": ["StandUpComedy", "AdviceAnimals", "Torontoevents", "whatsthisplant", "AskReddit", "Advice", "videos", "FoodToronto", "shittyfoodporn"]}, "joegonzalez722": {"comment": ["SuicideWatch", "LearnJapanese", "RokkaNoYuusha", "DecidingToBeBetter", "depression", "Advice", "starterpacks"], "submission": ["rant", "RokkaNoYuusha", "AnimeSketch", "sociopath", "anime", "DecidingToBeBetter", "depression", "Advice"]}, "kiwihichew": {"comment": [], "submission": ["Advice"]}, "reddituser633": {"comment": ["Advice"], "submission": ["photography", "weed", "depression", "Advice", "HangoutFest", "fakeid"]}, "anonim1215": {"comment": ["dating_advice"], "submission": ["Advice", "dating_advice"]}, "puppythrowaway512": {"comment": ["OldManDog", "dogpictures", "WhatsWrongWithYourDog", "Pets", "rarepuppers", "dogs", "lookatmydog", "PlottHounds", "Zoomies", "schnoodle", "WiggleButts", "Advice", "booptheheckinsnoot", "IDmydog", "puppy101"], "submission": ["cats", "IDmydog", "flippyflaps", "PuppySmiles", "Advice", "blurrypicturesofdogs", "tuckedinkitties", "Notakeonlythrow", "CasualConversation", "dogs", "lookatmydog", "PlottHounds", "booptheheckinsnoot", "schnoodle", "Zoomies", "aww", "puppy101", "AskVet", "squishypuppers", "WhatsWrongWithYourDog", "Pets", "rarepuppers", "Shrimping", "whatsthisbug", "thisismylifenow", "dogpictures", "puppies", "blop", "AnimalsBeingDerps", "FromKittenToCat", "FromPuppyToDog", "CalicoKittys", "RandomKindness"]}, "Carcity15": {"comment": ["confession", "ExNoContact", "grandrapids", "dating_advice", "BreakUps", "Advice", "relationship_advice", "socialskills"], "submission": ["confession", "relationships", "ExNoContact", "grandrapids", "dating_advice", "MakeNewFriendsHere", "UnsentLetters", "BreakUps", "Advice", "relationship_advice", "socialskills"]}, "icanbenamed": {"comment": ["Advice", "PewdiepieSubmissions"], "submission": ["Advice", "PewdiepieSubmissions", "relationships"]}, "y4z2": {"comment": ["dating_advice", "AskReddit", "funny", "Advice", "Cartalk", "relationship_advice", "socialskills"], "submission": ["confession", "dating_advice", "AskReddit", "Advice", "socialskills"]}, "jacobe35": {"comment": ["gaming", "worldnews", "Showerthoughts", "IAmA", "trashy", "atheism", "TwoXChromosomes", "funny", "tulsa", "Advice", "creepy", "politics", "CRedit", "reddit.com", "AskReddit", "RetailArbitrage", "askscience", "pics", "todayilearned", "technology", "JusticeServed", "legaladvice", "mildlyinteresting", "nottheonion", "UpliftingNews", "tifu", "videos", "news", "Christianity", "AdviceAnimals", "WTF", "Fuckthealtright", "gifs", "trees", "ImGoingToHellForThis"], "submission": ["iamverysmart", "legaladvice", "politics", "CRedit", "UFOs", "reddit.com", "AskReddit", "Advice", "funny", "tulsa", "askscience", "sanantonio"]}, "imgonnarot": {"comment": ["weightgain", "Hair", "WomensHealth", "Dermatology", "ptsd", "acne", "SelfHarmScars", "selfharm", "femalehairadvice", "TwoXChromosomes", "AskWomen", "IBD", "Periods", "Advice", "HairDye", "relationship_advice", "Accutane", "tattoos"], "submission": ["Dermatology", "canada", "weightgain", "SelfHarmScars", "IBD", "mentalhealth", "Advice", "Folliculitis", "WomensHealth", "tattoos", "femalehairadvice", "AskWomen", "Hair", "SkincareAddiction", "acne", "HairDye", "history", "selfharm", "Periods", "PaleMUA", "Accutane"]}, "SheiksLiteralyStalin": {"comment": ["relationships", "smashbros", "YMS", "Advice", "trees", "AmItheAsshole"], "submission": ["relationships", "smashbros", "Advice", "trees", "AmItheAsshole"]}, "Throwawayindecisao": {"comment": ["desabafos", "Trufemcels", "aznidentity", "Christianity", "scabies", "hapas", "brasil", "Clownworldwar", "FundieSnark", "Advice", "brasilivre"], "submission": ["Advice", "desabafos", "Christianity", "brasil"]}, "yas_sal1": {"comment": ["Advice", "relationship_advice"], "submission": ["Pinterest", "texas", "careeradvice", "Amman", "iphonehelp", "Advice", "relationship_advice"]}, "PlentiGaming": {"comment": ["PewdiepieSubmissions", "jailbreak", "SkincareAddiction", "relationship_advice", "iOSthemes", "wholesomememes", "apolloapp", "PS4Deals", "AskReddit", "financialindependence", "exjw"], "submission": ["NJTech", "PewdiepieSubmissions", "relationships", "me_irl", "jailbreak", "SkincareAddiction", "PlayStationPlus", "applehelp", "iOSthemes", "iphone", "Showerthoughts", "acne", "Advice", "exjw"]}, "ImNewDontBullyMe": {"comment": ["Jokes", "cats", "RoastMe", "vaxxhappened", "iamverysmart", "interestingasfuck", "Showerthoughts", "NoStupidQuestions", "atheism", "BreadStapledToTrees", "dankmemes", "softwaregore", "funny", "Advice", "dontdeadopeninside", "hmmm", "u_Okoinfo", "AskReddit", "CrappyDesign", "terriblefacebookmemes", "pics", "aww", "Sneks", "PewdiepieSubmissions", "MildlyVandalised", "StoppedWorking", "mildlyinfuriating", "memes", "mildlyinteresting", "thatHappened", "teenagers", "youngpeopleyoutube", "thisismylifenow", "Badfaketexts", "assholedesign", "entitledparents", "unexpectedhogwarts", "me_irl", "cursedimages", "sadcringe", "ihadastroke", "MurderedByWords", "cursedcomments", "dark_humor", "redditsings", "facepalm", "tumblr", "TwoSentenceHorror", "BoneAppleTea"], "submission": ["Jokes", "cats", "iamverysmart", "Showerthoughts", "atheism", "dankmemes", "softwaregore", "crappyoffbrands", "funny", "Advice", "dontdeadopeninside", "puns", "AskReddit", "CrappyDesign", "terriblefacebookmemes", "pics", "aww", "woooosh", "PewdiepieSubmissions", "StoppedWorking", "mildlyinfuriating", "memes", "mildlyinteresting", "thatHappened", "teenagers", "youngpeopleyoutube", "photoshopbattles", "assholedesign", "entitledparents", "TwoSentenceHorror", "ihadastroke", "cursedcomments", "redditsings", "HomeworkHelp", "facepalm", "lolcats"]}, "rekeesecivda": {"comment": ["Advice"], "submission": ["Advice"]}, "bitter_human": {"comment": ["crappycontouring", "Catloaf", "babyrhinogifs", "AccidentalRenaissance", "trashy", "books", "freefolk", "dankmemes", "TwoXChromosomes", "teefies", "HistoryPorn", "Advice", "Naturalhair", "DisneyEyes", "brushybrushy", "pornfree", "awfuleyebrows", "CringeAnarchy", "AskReddit", "shittyfoodporn", "blackladies", "CatSlaps", "happy", "nocontextpics", "quityourbullshit", "pornfreewomen", "rarepuppers", "SkincareAddiction", "BlackPeopleTwitter", "badtattoos", "Youniqueamua", "BeAmazed", "catbellies", "Embroidery", "curlyhair", "awfuleverything", "thisismylifenow", "GameTheorists", "curledfeetsies", "AskMen", "namenerds", "amiugly", "OldPhotosInRealLife", "MakeupAddiction", "exjw"], "submission": ["iamverysmart", "sex", "NoStupidQuestions", "TwoXChromosomes", "Naturalhair", "Advice", "LegalAdviceUK", "relationship_advice", "pornfree", "AskWomen", "AskReddit", "FemaleDatingStrategy", "Rateme", "antiMLM", "askwomenadvice", "blackladies", "quityourbullshit", "pornfreewomen", "SkincareAddiction", "legaladvice", "Dentistry", "mildlyinteresting", "curlyhair", "confession", "AskMen", "namenerds", "botany", "MakeupAddiction", "exjw"]}, "IAlreadyOrderedPizza": {"comment": ["harrypotter", "BigMouth", "Vans", "GetMotivated", "interestingasfuck", "relationship_advice", "DinosaurTattoos", "halloween", "politics", "Rammstein", "piercing", "Toreba", "AskReddit", "bunions", "BeautyBoxes", "Albuquerque", "antiMLM", "WWII", "gameofthrones", "Blooddonors", "tamagotchi", "SecurityClearance", "Clairvoyantreadings", "lawofattraction", "ToyotaTacoma", "CrossStitch", "Korn", "LushCosmetics", "BreakUps", "keto"], "submission": ["relationships", "Vans", "Advice", "relationship_advice", "tattoos", "Rammstein", "piercing", "KingOfTheHill", "Toreba", "bunions", "antiMLM", "Albuquerque", "Blooddonors", "toxicparents", "Buckethead", "tifu", "work", "Clairvoyantreadings", "ToyotaTacoma", "CrossStitch", "LushCosmetics", "BreakUps", "keto"]}, "honkitsaduck": {"comment": ["Advice"], "submission": ["Advice"]}, "zgv10094_loapq_com": {"comment": ["Advice"], "submission": ["Advice", "SuicideWatch"]}, "bilboshwaggins1480": {"comment": ["GetMotivated", "worldnews", "CryptoCurrency", "Advice", "remotework", "LifeProTips", "CasualConversation", "politics", "learnprogramming", "travel", "wallstreetbets", "AskReddit", "golf", "cscareerquestions", "StudentLoans", "datascience", "nosurf", "juststart", "DecidingToBeBetter", "mildlyinteresting", "intermittentfasting", "software", "pan_media", "movies", "Fitness", "jobs", "careerguidance", "findapath", "Unemployed", "Prosthetics", "EDM"], "submission": ["datascience", "cscareerquestions", "sad", "Showerthoughts", "questions", "jobs", "learnprogramming", "careerguidance", "AskReddit", "Advice", "learnjavascript", "Prosthetics", "FrontPage", "software"]}, "woollyhatt": {"comment": ["Madden", "RoastMe", "techsupport", "blackmagicfuckery", "niceguys", "interestingasfuck", "Showerthoughts", "killthecameraman", "ExplainBothSides", "BreadStapledToTrees", "penpals", "TalesFromYourServer", "swedishproblems", "therewasanattempt", "antiassholedesign", "offmychest", "NotHowGirlsWork", "TalesFromTheCustomer", "13or30", "hockey", "peopleofwalmart", "FiftyFifty", "TalesFromRetail", "AskAnAmerican", "awfuleverything", "hockeyplayers", "WatchPeopleDieInside", "college", "entitledparents", "gatekeeping", "TalesFromThePizzaGuy", "ihadastroke", "ThatsInsane", "KidsAreFuckingStupid", "gifs", "Cringetopia", "MomForAMinute", "TalesFromThePharmacy", "Jokes", "Whatcouldgowrong", "gaming", "DecreasinglyVerbose", "EA_NHL", "IAmA", "humblebrag", "Stuck10YearsBehind", "holdmyjuicebox", "TooAfraidToAsk", "Cooking", "MaliciousCompliance", "dontdeadopeninside", "Humanoidencounters", "cleanjokes", "Vent", "femalehairadvice", "RocketLeagueFriends", "NoahGetTheBoat", "goldenknights", "RocketLeagueEsports", "internetparents", "todayilearned", "ladybonersgw", "AskVet", "holdmyfeedingtube", "NHLHUT", "TargetedShirts", "GlobalOffensive", "selfie", "videos", "badroommates", "talesfromcallcenters", "food", "Unexpected", "KitchenConfidential", "Tekken", "yiffinhell", "entitledparentsmemes", "NHL19", "Puninternalaffairs", "AskDocs", "nononono", "AMA", "GiftIdeas", "svenskpolitik", "funny", "foundthemobileuser", "EntitledBitch", "techhelp", "LetsNotMeet", "badwomensanatomy", "perfectlycutscreams", "RLCustomTraining", "riskyclick", "yesyesyesyesno", "meirl", "OldSchoolCool", "Rocket_League", "entitledkids", "pointlesslygendered", "aww", "HadToHurt", "sploot", "christianmemes", "Assistance", "explainlikeimfive", "findareddit", "CongratsLikeImFive", "nextfuckinglevel", "assholetax", "whatsthisbug", "Coronavirus", "fearsineverknewihad", "Wellthatsucks", "dontyouknowwhoiam", "IdiotsNearlyDying", "IdiotsInCars", "Supraball", "Polytopia", "dontputyourdickinthat", "birdswithhumanpenises", "OopsDidntMeanTo", "TattooDesigns", "TalesFromTheFrontDesk", "delusionalartists", "GetMotivated", "iamverysmart", "ChoosingBeggars", "delusionalcraigslist", "TrueOffMyChest", "sports", "Advice", "HydroHomies", "RocketLeagueSchool", "AmItheAsshole", "relationship_advice", "SweatyPalms", "myfriendwantstoknow", "ExtremeCarCrashes", "RocketLeague", "restofthefuckingowl", "tattoo", "HistoryMemes", "AskReddit", "wildlyinfuriating", "Minecraft", "toastme", "iamverybadass", "confusing_perspective", "agedlikemilk", "ftm", "oldpeoplefacebook", "imsorryjon", "tifu", "ComedyCemetery", "shittysuperpowers", "unpopularopinion", "sweden", "assholedesign", "pettyrevenge", "Cubers", "pestcontrol", "nameaserver", "IDontWorkHereLady", "JUSTNOFAMILY", "Twitch", "hearthstone"], "submission": ["TattooDesigns", "gaming", "delusionalartists", "techsupport", "EA_NHL", "AskDocs", "GiftIdeas", "AMA", "TrueOffMyChest", "DotA2", "TooAfraidToAsk", "Advice", "swedishproblems", "techhelp", "RLCustomTraining", "RocketLeague", "restofthefuckingowl", "dogs", "Vent", "tattoo", "RocketLeagueFriends", "AskReddit", "aww", "AskVet", "explainlikeimfive", "findareddit", "NHLHUT", "ftm", "whatsthisbug", "tifu", "Sverige", "pestcontrol", "Tekken", "EASPORTS_NHL", "Supraball", "Polytopia", "hearthstone"]}, "cristensa": {"comment": ["Winnipeg", "LoseitChallenges", "Team_Cassiopeia", "SampleSize", "FoodPorn", "LSAT", "Divination", "MakeNewFriendsHere", "lawschooladmissions", "progresspics", "umanitoba", "AskReddit", "funny"], "submission": ["cats", "SupermodelCats", "language_exchange", "SampleSize", "23andme", "MakeNewFriendsHere", "umanitoba", "Advice", "aww"]}, "be_nice_to__me_plz": {"comment": ["gaming", "Showerthoughts", "cringe", "AccidentalRenaissance", "sketches", "ChoosingBeggars", "likeus", "depression", "ContagiousLaughter", "childfree", "funny", "Advice", "bullying", "LifeProTips", "tattoos", "roosterteeth", "HumansBeingBros", "therewasanattempt", "perfectlycutscreams", "creepy", "araragi", "OldSchoolCool", "AskReddit", "pics", "todayilearned", "initiald", "insanepeoplefacebook", "pcmasterrace", "PS3", "VRchat", "ADHD", "comics", "creepyPMs", "regularcarreviews", "Commodore", "MechanicAdvice", "anime", "mildlyinteresting", "tifu", "videos", "thighdeology", "AnimeSketch", "Bossfight", "ihavesex", "Vive", "Smite", "gifs", "SuperMega", "animegifs", "Anime_Art", "gamegrumps"], "submission": ["police", "ADHD", "MechanicAdvice", "Commodore", "depression", "AskReddit", "pcmasterrace", "Advice", "PS3"]}, "PlnkFloyd": {"comment": ["Whatcouldgowrong", "gaming", "h3h3productions", "depression", "sports", "depression_help", "Anxiety", "bimbofetish", "relationship_advice", "SuicideWatch", "gonewild", "politics", "nofriends", "PoliticalHumor", "AskWomen", "Brewers", "OldSchoolCool", "AskReddit", "pics", "aww", "battlefield_one", "SkincareAddiction", "housekeeping", "JusticeServed", "mildlyinteresting", "science", "MkeBucks", "movies", "AskMen", "gifs"], "submission": ["Whatisthis", "Tinder", "relationships", "RandomActsOfMuffDive", "SkincareAddiction", "housekeeping", "Dreams", "socialanxiety", "battlefield_4", "AskWomen", "depression", "amiugly", "VPN", "depression_help", "NoFap", "lonely", "Advice", "relationship_advice", "conan", "RandomActsOfBlowJob"]}, "diabeetusboy": {"comment": ["Seattle", "interestingasfuck", "Showerthoughts", "conspiracy", "bestof", "Mindfulness", "financialindependence", "DumpsterDiving", "SeattleUrbEx", "electronicmusic", "politics", "LSD", "minnesotavikings", "cigars", "AlbumArtPorn", "CombatFootage", "holdmybeer", "pics", "The_Donald", "thalassophobia", "AmateurRoomPorn", "EarthPorn", "insanepeoplefacebook", "DeepFriedMemes", "fakealbumcovers", "photography", "ar15", "legaladvice", "Documentaries", "hiphop", "BlackPeopleTwitter", "motivation", "shrooms", "modernwarfare", "Art", "trap", "reactiongifs", "photoshopbattles", "college", "movies", "gatekeeping", "gundeals", "space", "PoliceChases", "libtard", "Music", "raining", "gifs", "starterpacks", "suicidebywords", "youseeingthisshit", "CarAV", "HillaryForPrison", "fakeid", "Jokes", "gaming", "urbanexploration", "TheRedPill", "ufc", "IAmA", "trashy", "dankmemes", "postprocessing", "ak47", "getdisciplined", "graphic_design", "fantasyfootball", "Flipping", "ImpeachTrump", "guns", "investing", "wallstreetbets", "JusticePorn", "MovieMistakes", "MensRights", "todayilearned", "Nicegirls", "Physical_Removal", "itookapicture", "seduction", "aves", "dirtykikpals", "TargetedShirts", "weekendgunnit", "pinkfloyd", "nottheonion", "UpliftingNews", "QuotesPorn", "CozyPlaces", "videos", "science", "Anarchism", "BustyPetite", "surrealmemes", "food", "news", "nfl", "GavinMcInnes", "trees", "recruiting", "FashionReps", "SeattleWA", "cats", "GreenBayPackers", "apexlegends", "Libertarian", "MarchAgainstTrump", "KotakuInAction", "TwoXChromosomes", "StreetFights", "Frisson", "funny", "tattoos", "cringepics", "options", "Odesza", "Lithuaniakittens", "selfimprovement", "CampingandHiking", "OldSchoolCool", "futurebeats", "AbsoluteUnits", "aww", "listentothis", "rarepuppers", "explainlikeimfive", "HongKong", "Firefighting", "mildlyinteresting", "oddlysatisfying", "Conservative", "photocritique", "gadgets", "WTF", "Futurology", "MurderedByWords", "audiophile", "unstirredpaint", "iamverysmart", "worldnews", "GetMotivated", "streetwear", "malelivingspace", "bikesgonewild", "books", "madlads", "sports", "indianpeoplefacebook", "nyjets", "Advice", "RobinHood", "49ers", "cuntsdownunder", "AnimalsBeingJerks", "cocaine", "creepy", "VPN", "AskReddit", "CrappyDesign", "sportsbook", "diabetes", "recruitinghell", "Bad_Cop_No_Donut", "JordanPeterson", "KenM", "copypasta", "Psychonaut", "mildlyinfuriating", "Sneakers", "tacticalgear", "4Runner", "boottoobig", "bodybuilding", "progresspics", "hiphopheads", "glitch_art", "Frugal", "ScarySigns", "tifu", "thatHappened", "malelifestyle", "motorcycles", "stocks", "Fitness", "AdviceAnimals", "careerguidance", "MealPrepSunday", "holdmycosmo", "The_Seattle", "ShitLiberalsSay", "ncaaBBallStreams", "EDM"], "submission": ["me_irl_video", "cats", "relationships", "techsupport", "streetwear", "Showerthoughts", "asktrp", "mentalhealth", "Advice", "graphic_design", "SeattleUrbEx", "cocaine", "dxm", "electronicmusic", "LSD", "Flipping", "selfimprovement", "CampingandHiking", "MemeEconomy", "VPN", "wallstreetbets", "AskReddit", "Drugs", "The_Donald", "HomeDepot", "Physical_Removal", "itookapicture", "r4r", "ar15", "legaladvice", "photography", "hiphop", "Psychonaut", "4Runner", "Repsneakers", "progresspics", "askseddit", "CozyPlaces", "trap", "Conservative", "college", "photocritique", "motorcycles", "BudgetAudiophile", "Fitness", "careerguidance", "MurderedByWords", "EDM", "CarAV", "fakeid"]}, "remsterbay": {"comment": ["food", "slavelabour", "jobs", "selfimprovement", "overcoming", "Advice", "homeless", "socialskills"], "submission": ["help", "CasualConversation", "needadvice", "slavelabour", "offmychest", "Advice"]}, "thoraway6262": {"comment": [], "submission": ["Advice"]}, "cantletyadown": {"comment": ["Nepal", "WatchPeopleDieInside", "news", "holdmyfeedingtube", "pkmntcgtrades", "pkmntcgcollections", "RiftForSale", "mildlyinteresting", "sneakermarket", "AskReddit", "Advice", "pics"], "submission": ["Nepal", "pkmntcgtrades", "pkmntcgcollections", "AskReddit", "Advice"]}, "idris-tardis": {"comment": ["halifax", "IAmA", "AskDocs", "AMA", "cantsleep", "DadForAMinute", "PCOS", "waiting_to_try", "Advice", "rehabtherapy", "Maine", "therapists", "AskWomen", "AskReddit", "April2020Bumpers", "pansexual", "AbsoluteUnits", "toastme", "aww", "insomnia", "FreeCompliments", "internetparents", "ttcafterloss", "May2020Bumpers", "BabyBumps", "xxfitness", "Superbowl", "nextfuckinglevel", "AskAnAmerican", "ibs", "ratemyvoice", "OccupationalTherapy"], "submission": ["April2020Bumpers", "ttcafterloss", "therapists", "halifax", "ibs", "AskDocs", "PlusSize", "cantsleep", "BabyBumps", "xxfitness", "birthcontrol", "PCOS", "UnsentLetters", "DadForAMinute", "waiting_to_try", "Advice", "askdoctors", "OccupationalTherapy", "TryingForABaby", "breastcancer"]}, "Lawrence_A_Alexande": {"comment": [], "submission": ["Advice"]}, "MTMDark": {"comment": ["Vaping", "SampleSize", "CODZombies", "nuzlocke", "pokemon", "memes", "roll20LFG", "Vaping101", "funny", "Advice", "tipofmytongue", "tattoos"], "submission": ["Vaping", "SampleSize", "Shitty_Car_Mods", "legaladvice", "Vent", "pokemon", "Achievement_Hunter", "Advice", "Twitch", "tipofmytongue"]}, "glamarz": {"comment": ["gaming", "relationships", "ExNoContact", "techsupport", "blackmagicfuckery", "streetwear", "sex", "crafts", "TrueOffMyChest", "weed", "depression", "Advice", "Anxiety", "relationship_advice", "CasualUK", "needadvice", "offmychest", "FortNiteBR", "somethingimade", "LSD", "treedibles", "AskReddit", "whatisthisthing", "MDMA", "entwives", "britishmilitary", "sewing", "UnsentLetters", "trees", "Sims4", "painting"], "submission": ["relationships", "techsupport", "sex", "crafts", "depression", "Advice", "Anxiety", "relationship_advice", "FortNiteBR", "LSD", "offmychest", "treedibles", "whatisthisthing", "MDMA", "explainlikeimfive", "legaladvice", "coincollecting", "entwives", "britishmilitary", "whatsthisbug", "thatHappened", "curledfeetsies", "sewing", "BreakUps", "beauty", "trees"]}, "SomeRandomLoser1": {"comment": ["Advice"], "submission": ["Advice", "offmychest"]}, "monyoumental": {"comment": ["Jokes", "Whatcouldgowrong", "blackmagicfuckery", "interestingasfuck", "PublicFreakout", "Showerthoughts", "UnethicalLifeProTips", "IAmA", "tooktoomuch", "britishproblems", "atheism", "TrueOffMyChest", "funny", "Advice", "vandwellers", "LifeProTips", "HumansBeingBros", "personalfinance", "AccidentalRacism", "WhitePeopleTwitter", "mechanical_gifs", "officialmollybennett", "Tools", "polyamory", "GreenAndPleasant", "lostgeneration", "whatisthisthing", "AskReddit", "CrappyDesign", "FUCKYOUINPARTICULAR", "todayilearned", "EarthPorn", "AssemblyLineGame", "iamverybadass", "electricians", "turning", "LateStageCapitalism", "dashcamgifs", "dank_meme", "instantkarma", "explainlikeimfive", "Roadcam", "BetterEveryLoop", "nothingeverhappens", "communism101", "memes", "nevertellmetheodds", "PraiseTheCameraMan", "mildlyinteresting", "Frugal", "mildlyinfuriating", "Tucson", "BeAmazed", "history", "videos", "tifu", "povertyfinance", "GTAorRussia", "bigdickproblems", "Skookum", "news", "AskOuija", "assholedesign", "IdiotsInCars", "pettyrevenge", "gatekeeping", "ShitAmericansSay", "WTF", "Sinkpissers", "conduitporn", "gifs", "NotMyJob"], "submission": ["assholedesign", "britishproblems", "Frugal", "whatisthisthing", "Advice"]}, "kittydoom99": {"comment": ["darksouls3", "relationships", "UnethicalLifeProTips", "AskDocs", "ForeverAlone", "childfree", "TooAfraidToAsk", "lonely", "skinwalkers", "Advice", "NEET", "penpals", "SuicideWatch", "single", "grandorder", "AskReddit", "askwomenadvice", "manga", "jobcorps", "mildlyinfuriating", "MuayThai", "MakeNewFriendsHere", "confession", "AskRedditAfterDark", "ForeverAloneDating", "dating_advice", "Sekiro", "watamote"], "submission": ["darksouls3", "ForeverAloneDating", "u_kittydoom99", "AskDocs", "mildlyinfuriating", "WeightLossAdvice", "Advice", "tifu"]}, "sadnessboye": {"comment": ["AskOuija", "darkjokes", "madlads", "PUBGMobile", "AMA", "im14andthisisdeep", "memes", "JustCause", "AskReddit", "Advice", "Seaofthieves"], "submission": ["AskOuija", "PUBGMobile", "AMA", "im14andthisisdeep", "JustCause", "AskReddit", "Advice", "Seaofthieves"]}, "throwawaygyhrt": {"comment": [], "submission": ["confession", "nosleep", "Nightmares", "Dreams", "Needafriend", "NoStupidQuestions", "HealthAnxiety", "Advice", "Anxiety", "poop"]}, "Mika000": {"comment": ["formula1", "costumeideas", "TrueOffMyChest", "TransSpace", "translator", "Advice", "lgbt", "millionairemakers", "guessmyage", "asktransgender", "asexuality", "CasualConversation", "firstimpression", "Vent", "OldSchoolCool", "AskReddit", "whatisthisthing", "marvelstudios", "pics", "tipofmytongue", "transtimelines", "transpositive", "nyc", "FTMFitness", "MakeNewFriendsHere", "ftm", "ask_transgender", "selfie", "Art", "FtMpassing", "teenagers", "transpassing", "unpopularopinion", "gatekeeping", "duolingo", "FTMMen", "MurderedByWords", "facepalm", "What"], "submission": ["relationships", "costumeideas", "Advice", "translator", "bullying", "guessmyage", "Poems", "asktransgender", "language_exchange", "asexuality", "CasualConversation", "firstimpression", "Vent", "Dreams", "CatsStandingUp", "whatisthisthing", "AskReddit", "marvelstudios", "pics", "tipofmytongue", "Handwriting", "transtimelines", "transpositive", "nyc", "findareddit", "FTMFitness", "MakeNewFriendsHere", "ftm", "mildlyinteresting", "Adoption", "teenagers", "curledfeetsies", "transpassing", "unpopularopinion", "movies", "duolingo", "FTMMen"]}, "thr0w1taway44": {"comment": ["Advice", "relationship_advice"], "submission": ["Advice", "moviepass", "relationship_advice"]}, "ingham210": {"comment": ["RoastMe", "Showerthoughts", "seinfeldgifs", "Borderlands", "R6STeams", "lfg", "tightdresses", "greenday", "youtubehaiku", "socialskills", "NintendoSwitch", "Guitar", "offmychest", "TalesFromTheCustomer", "fatpeoplehate", "PlayStationPlus", "pics", "singing", "UOW", "CallOfDuty", "musictheory", "cars", "counting", "reactiongifs", "awfuleverything", "Ingrown_Toenails", "movies", "PS4", "clevercomebacks", "WeAreTheMusicMakers", "Music", "amiugly", "Colorization", "gifs", "Caddicarus", "FIFA", "onetruegod", "guitarteachers", "gaming", "Punny", "sydney", "relationships", "retorted", "IAmA", "Fifa13", "fffffffuuuuuuuuuuuu", "chelseafc", "GamePhysics", "Songwriting", "CrazyIdeas", "soccer", "macgaming", "OneYearOn", "santashelpers", "humor", "drums", "indieheads", "seduction", "MetalMemes", "pinkfloyd", "Bass", "videos", "audioengineering", "PrayerOrSlayer", "AngelsAndAirwaves", "AskMen", "JohnMayer", "australia", "medical", "CodAW", "RedHotChiliPeppers", "reddeadredemption", "outside", "GiftIdeas", "Blink182", "depression", "self", "BreakUps", "confessions", "funny", "worldcup", "iamatotalpieceofshit", "metalgearsolid", "Learnmusic", "WritingPrompts", "seinfeld", "CasualConversation", "FifaCareers", "writing", "guitarpedals", "skyrim", "aww", "PS3", "Handwriting", "listentothis", "GarageRock", "malefashionadvice", "LearnUselessTalents", "mildlyinteresting", "oddlysatisfying", "brooklynninenine", "picrequests", "teenagers", "weightroom", "EqualAttraction", "Howwastoday", "punchablefaces", "ktane", "lifehacks", "facepalm", "needabro", "LetsChat", "Blackops4", "straya", "cringe", "ChoosingBeggars", "books", "DunderMifflin", "Advice", "LifeProTips", "relationship_advice", "personalfinance", "shittyaskscience", "AskReddit", "Minecraft", "ScenesFromAHat", "dadjokes", "guitarpedalsjerk", "4chan", "Jazz", "RandomActsOfGaming", "Pantera", "TheSimpsons", "AdviceAnimals", "Fitness", "Metalcore", "livesound", "FREE", "HomeworkHelp", "Damnthatsinteresting", "SpideyMeme"], "submission": ["cakeday", "gaming", "sydney", "crashbandicoot", "RoastMe", "retorted", "GetMotivated", "outside", "Fifa13", "GiftIdeas", "NoStupidQuestions", "lfg", "Blink182", "depression", "DunderMifflin", "lcfc", "BreakUps", "funny", "confessions", "Advice", "relationship_advice", "socialskills", "GamePhysics", "Songwriting", "infamous", "SuicideWatch", "metalgearsolid", "getdisciplined", "WritingPrompts", "seinfeld", "personalfinance", "NintendoSwitch", "santashelpers", "Guitar", "CasualConversation", "offmychest", "FifaCareers", "writing", "guitarpedals", "IWantToLearn", "AskReddit", "skyrim", "pics", "aww", "ThisIsOurMusic", "PS3", "DAE", "drums", "photography", "dadjokes", "seduction", "guitarpedalsjerk", "pinkfloyd", "books", "askseddit", "PS4Share", "musictheory", "retsupurae", "audioengineering", "teenagers", "Jazz", "Ingrown_Toenails", "AngelsAndAirwaves", "weightroom", "JohnMayer", "AdviceAnimals", "australia", "Fitness", "jobs", "dating_advice", "EqualAttraction", "WeAreTheMusicMakers", "Music", "medical", "amiugly", "HomeworkHelp", "Colorization", "needabro", "ImGoingToHellForThis", "FIFA"]}, "Jumpman-x": {"comment": ["Blackops4", "gaming", "reddeadredemption", "worldnews", "StreamersGoneWild", "BravoRealHousewives", "Warframe", "FearTheWalkingDead", "trashy", "theworldisflat", "wow", "ChoosingBeggars", "iamatotalpieceofshit", "SiegeAcademy", "thedivision", "fo4vr", "funny", "Advice", "EliteDangerous", "AmItheAsshole", "LifeProTips", "Blizzard", "swtor", "ems", "rage", "AtlasPC", "classicwow", "elderscrollsonline", "NewToEMS", "AskReddit", "Astronomy", "pics", "thalassophobia", "todayilearned", "insanepeoplefacebook", "Nicegirls", "NSFW_Japan", "opiates", "woahdude", "starcitizen", "guineapigs", "CODZombies", "JusticeServed", "modernwarfare", "Cringetopia", "nevertellmetheodds", "SocialMediaSluts", "OCD", "mildlyinteresting", "halo", "AnthemTheGame", "Wellthatsucks", "JizzedToThis", "teenagers", "pan_media", "news", "PCRedDead", "TheMandalorianTV", "nipslips", "MGTOW", "AskMen", "buildapc", "DestinyTheGame", "titanfall", "gatekeeping", "space", "Fireteams", "ColorizedHistory", "gtaonline", "LivestreamFail", "Vive", "EDM", "pcmasterrace", "Gaming4Gamers", "ImGoingToHellForThis", "alvajay"], "submission": ["opiates", "Blackops4", "starcitizen", "guineapigs", "Showerthoughts", "needadvice", "FearTheWalkingDead", "Rainbow6", "wow", "gtaonline", "NewToEMS", "Vive", "Advice", "AnthemTheGame", "EDM"]}, "GlintPhantom": {"comment": ["Themepark", "ElgatoGaming", "ankhbotR2", "headphones", "buildapc", "introvert", "loseit", "buildmeapc", "friendsafari", "dating_advice", "selfimprovement", "PickAnAndroidForMe", "Twitch", "socialskills"], "submission": ["Themepark", "ElgatoGaming", "relationships", "pcgaming", "friendsafari", "manners", "Advice", "disabled", "socialskills", "AdvertiseYourVideos", "ankhbotR2", "Steam", "selfimprovement", "TowerDefense", "AskReddit", "IWantToLearn", "marvelstudios", "friendship", "loseit", "PickAnAndroidForMe", "puzzles", "buildapc", "askpsychology", "introvert", "buildmeapc", "MovieSuggestions", "introverts", "pcmasterrace", "Twitch"]}, "munchinbeavers": {"comment": ["beatsbydre", "BikiniBottomTwitter", "Madden", "cats", "leafs", "DetroitRedWings", "mlb", "NintendoSwitch", "Journalism", "apple", "ThomaHawkShow", "AskReddit", "Blogging", "linux", "hbo", "aww", "mac", "podcasts", "hockey", "hardknocks", "windsorontario", "photography", "hockeyjerseys", "workout", "booksuggestions", "hockeyplayers", "nba", "warriors", "Fitness", "pokemon"], "submission": ["Madden", "cats", "Advice", "Anxiety", "NintendoSwitch", "Journalism", "ebooks", "mancave", "macbookair", "apple", "hbo", "Blogging", "fantasyhockey", "aww", "podcasts", "hockey", "windsorontario", "mealprep", "photography", "hockeyjerseys", "workout", "booksuggestions", "hockeyplayers", "IPTV", "Fitness", "pokemon"]}, "actual_raccoon": {"comment": ["vegan", "HelpMeFind", "canada", "NoStupidQuestions", "OCPoetry", "thesims", "Glitch_in_the_Matrix", "Advice", "penpals", "butchlesbians", "DoesAnybodyElse", "Aquariums", "scienceofdeduction", "CasualConversation", "TheGirlSurvivalGuide", "AskWomen", "whatisthisthing", "AskReddit", "bisexual", "ottawa", "askwomenadvice", "femalefashionadvice", "Pets", "SkincareAddiction", "loseit", "notebooks", "UofT", "LuLaNo", "ImmigrationCanada", "LGBTeens", "DreamDaddy", "fountainpens", "FoodFantasy", "ShitAmericansSay", "AskHistorians", "namenerds", "IncelTears", "MakeupAddiction", "Sims4", "highschool", "AsianParentStories"], "submission": ["vegan", "HelpMeFind", "NoStupidQuestions", "OCPoetry", "thesims", "Glitch_in_the_Matrix", "Advice", "penpals", "butchlesbians", "DoesAnybodyElse", "u_actual_raccoon", "Aquariums", "asktransgender", "rant", "scienceofdeduction", "CasualConversation", "Needafriend", "Dreams", "offmychest", "writing", "whatisthisthing", "ottawa", "internetparents", "askwomenadvice", "femalefashionadvice", "Hair", "shittyaquariums", "Pets", "SkincareAddiction", "loseit", "asmr", "notebooks", "UofT", "LGBTeens", "DreamDaddy", "SuggestALaptop", "fountainpens", "FoodFantasy", "AskHistorians", "dating_advice", "namenerds", "MakeupAddiction", "Sims4", "AsianParentStories"]}, "BooksCatsnTea": {"comment": [], "submission": ["Advice", "Assistance", "Charity"]}, "NarcoDog": {"comment": ["worldnews", "Showerthoughts", "bald", "JoeRogan", "funny", "Advice", "LegalAdviceUK", "SamandTolki", "SubredditDrama", "DIY", "OldSchoolCool", "AskReddit", "OpenUniversity", "pics", "aww", "buildapcforme", "explainlikeimfive", "fightporn", "gifs", "PUBATTLEGROUNDS", "videos", "Drama", "fo4", "news", "movies", "gadgets", "Fitness", "dataisbeautiful"], "submission": ["buildapcforme", "LegalAdviceUK", "Advice", "AskReddit"]}, "Culltro": {"comment": ["playrust", "Vaping", "CircleofTrust", "23andme", "The_Donald"], "submission": ["discordapp", "DebateAltRight", "CircleofTrust", "23andme", "meme", "army", "AskReddit", "Advice", "videos", "virginvschad"]}, "ChadWantsNudoru": {"comment": ["Advice", "AskReddit"], "submission": ["Advice", "PhotoshopRequest"]}}